block3.cpython-310-x86_64-linux-gnu.so
pyblock3-0.2.8.dist-info/RECORD
pyblock3-0.2.8.dist-info/LICENSE
pyblock3-0.2.8.dist-info/WHEEL
pyblock3-0.2.8.dist-info/METADATA
pyblock3-0.2.8.dist-info/top_level.txt
pyblock3.libs/libmkl_avx512.so.1
pyblock3.libs/libmkl_avx2.so.1
pyblock3.libs/libmkl_intel_lp64-eeafede9.so.1
pyblock3.libs/libmkl_core-a1f8e95a.so.1
pyblock3.libs/libgomp-f7e03b3e.so.1.0.0
pyblock3.libs/libmkl_gnu_thread-76126a9d.so.1
pyblock3/__init__.py
pyblock3/fcidump.py
pyblock3/hamiltonian.py
pyblock3/heisenberg.py
pyblock3/gaussian/__init__.py
pyblock3/gaussian/core.py
pyblock3/algebra/__init__.py
pyblock3/algebra/fermion_encoding.py
pyblock3/algebra/flat_functor.py
pyblock3/algebra/core.py
pyblock3/algebra/mps.py
pyblock3/algebra/einsum.py
pyblock3/algebra/fermion_ops.py
pyblock3/algebra/fermion_symmetry.py
pyblock3/algebra/fermion_large.py
pyblock3/algebra/mpe.py
pyblock3/algebra/fermion_setting.py
pyblock3/algebra/flat.py
pyblock3/algebra/linalg.py
pyblock3/algebra/funcs.py
pyblock3/algebra/integrate.py
pyblock3/algebra/fermion.py
pyblock3/algebra/symmetry.py
pyblock3/algebra/ad/__init__.py
pyblock3/algebra/ad/core.py
pyblock3/algebra/ad/mps.py
pyblock3/algebra/ad/fermion_ops.py
pyblock3/algebra/ad/flat_impl.py
pyblock3/algebra/ad/flat.py
pyblock3/algebra/ad/fermion.py
pyblock3/algebra/tests/__init__.py
pyblock3/algebra/tests/test_boson_cpp.py
pyblock3/algebra/tests/test_fermion_ops.py
pyblock3/algebra/tests/test_fermion_python.py
pyblock3/algebra/tests/test_symmetry.py
pyblock3/algebra/tests/test_fermion_cpp.py
pyblock3/algebra/tests/test_fermion_large.py
pyblock3/algebra/tests/test_boson_python.py
pyblock3/algebra/impl/__init__.py
pyblock3/algebra/impl/flat.py
pyblock3/block2/__init__.py
pyblock3/block2/io.py
pyblock3/block2/hamil.py
pyblock3/algorithms/__init__.py
pyblock3/algorithms/core.py
pyblock3/algorithms/tddmrg.py
pyblock3/algorithms/green.py
pyblock3/algorithms/dmrg.py
pyblock3/algorithms/linear.py
pyblock3/algorithms/tests/__init__.py
pyblock3/algorithms/tests/test_dmrg.py
pyblock3/algorithms/tests/test_soc.py
