Metadata-Version: 2.1
Name: pyblock3
Version: 0.2.8
Summary: An efficient python block-sparse tensor and MPS/DMRG library.
Home-page: https://github.com/block-hczhai/pyblock3-preview
Author: Huanchen Zhai, Yang Gao, and Garnet K.-L. Chan
Author-email: hczhai@ucla.edu
License: LICENSE
License-File: LICENSE
Requires-Dist: mkl (==2021.4)
Requires-Dist: mkl-include
Requires-Dist: numpy (<1.23.0)
Requires-Dist: psutil
Requires-Dist: pybind11 (<=2.10.1)
Requires-Dist: intel-openmp
Requires-Dist: cmake
